federated/__init__.py
federated/common.py
federated/fedarated_client.py
federated_client-0.1.dist-info/METADATA
federated_client-0.1.dist-info/WHEEL
federated_client-0.1.dist-info/top_level.txt
federated_client-0.1.dist-info/RECORD
